LICENSE
README.md
pyproject.toml
setup.cfg
setup.py
hiddenlayer/__init__.py
hiddenlayer/clients/__init__.py
hiddenlayer/clients/clients.py
hiddenlayer/config/__init__.py
hiddenlayer/config/config.py
hiddenlayer_python.egg-info/PKG-INFO
hiddenlayer_python.egg-info/SOURCES.txt
hiddenlayer_python.egg-info/dependency_links.txt
hiddenlayer_python.egg-info/requires.txt
hiddenlayer_python.egg-info/top_level.txt