Metadata-Version: 2.1
Name: hiddenlayer-python
Version: 0.0.8
Summary: HiddenLayer
Home-page: https://www.github.com/hiddenlayersec/hiddenlayer-python
Author: HiddenLayer
Author-email: contact@hiddenlayer.com
License: UNKNOWN
Platform: UNKNOWN
Classifier: Intended Audience :: Developers
Classifier: Operating System :: OS Independent
Classifier: Programming Language :: Python :: 3.9
License-File: LICENSE
